aocd_example_parser/__init__.py
aocd_example_parser/examples.json
aocd_example_parser/extraction.py
aocd_example_parser/plugins.py
aocd_example_parser/util.py
aocd_example_parser-2025.12.12.dist-info/entry_points.txt
aocd_example_parser-2025.12.12.dist-info/licenses/LICENSE
aocd_example_parser-2025.12.12.dist-info/WHEEL
aocd_example_parser-2025.12.12.dist-info/METADATA
aocd_example_parser-2025.12.12.dist-info/RECORD
