Metadata-Version: 2.4
Name: aocd-example-parser
Version: 2025.12.12
Summary: Implementation of example parser plugins for advent-of-code-data
Author-email: Wim Jeantine-Glenn <hey@wimglenn.com>
Requires-Python: >=3.9
License-Expression: MIT
Classifier: Intended Audience :: Developers
Classifier: Programming Language :: Python :: 3
Classifier: Topic :: Software Development :: Libraries
Classifier: Topic :: Games/Entertainment :: Puzzle Games
License-File: LICENSE
Project-URL: Homepage, https://github.com/wimglenn/aocd-example-parser
